{
  "openapi": "3.1.0",
  "info": {
    "title": "Plerion API",
    "version": "0.1.0"
  },
  "paths": {
    "/captures": {
      "get": {
        "tags": [
          "captures"
        ],
        "summary": "Get Captures",
        "operationId": "get_captures",
        "parameters": [
          {
            "name": "ids",
            "in": "query",
            "required": false,
            "schema": {
              "anyOf": [
                {
                  "type": "array",
                  "items": {
                    "type": "string",
                    "format": "uuid"
                  }
                },
                {
                  "type": "null"
                }
              ],
              "description": "Optional list of Ids to filter by",
              "title": "Ids"
            },
            "description": "Optional list of Ids to filter by"
          }
        ],
        "responses": {
          "200": {
            "description": "Successful Response",
            "content": {
              "application/json": {
                "schema": {
                  "type": "array",
                  "items": {
                    "$ref": "#/components/schemas/CaptureModel"
                  },
                  "title": "Response Get Captures"
                }
              }
            }
          },
          "422": {
            "description": "Validation Error",
            "content": {
              "application/json": {
                "schema": {
                  "$ref": "#/components/schemas/HTTPValidationError"
                }
              }
            }
          }
        }
      },
      "post": {
        "tags": [
          "captures"
        ],
        "summary": "Create Capture",
        "operationId": "create_capture",
        "requestBody": {
          "required": true,
          "content": {
            "application/json": {
              "schema": {
                "$ref": "#/components/schemas/Body_create_capture"
              }
            }
          }
        },
        "responses": {
          "200": {
            "description": "Successful Response",
            "content": {
              "application/json": {
                "schema": {
                  "$ref": "#/components/schemas/CaptureModel"
                }
              }
            }
          },
          "422": {
            "description": "Validation Error",
            "content": {
              "application/json": {
                "schema": {
                  "$ref": "#/components/schemas/HTTPValidationError"
                }
              }
            }
          }
        }
      }
    },
    "/captures/{id}": {
      "get": {
        "tags": [
          "captures"
        ],
        "summary": "Get Capture",
        "operationId": "get_capture",
        "parameters": [
          {
            "name": "id",
            "in": "path",
            "required": true,
            "schema": {
              "type": "string",
              "format": "uuid",
              "title": "Id"
            }
          }
        ],
        "responses": {
          "200": {
            "description": "Successful Response",
            "content": {
              "application/json": {
                "schema": {
                  "$ref": "#/components/schemas/CaptureModel"
                }
              }
            }
          },
          "422": {
            "description": "Validation Error",
            "content": {
              "application/json": {
                "schema": {
                  "$ref": "#/components/schemas/HTTPValidationError"
                }
              }
            }
          }
        }
      }
    },
    "/captures/{id}/tar": {
      "put": {
        "tags": [
          "captures"
        ],
        "summary": "Upload Capture Tar",
        "operationId": "upload_capture_tar",
        "parameters": [
          {
            "name": "id",
            "in": "path",
            "required": true,
            "schema": {
              "type": "string",
              "format": "uuid",
              "title": "Id"
            }
          }
        ],
        "responses": {
          "307": {
            "description": "Successful Response",
            "content": {
              "application/json": {
                "schema": {}
              }
            }
          },
          "422": {
            "description": "Validation Error",
            "content": {
              "application/json": {
                "schema": {
                  "$ref": "#/components/schemas/HTTPValidationError"
                }
              }
            }
          }
        },
        "requestBody": {
          "required": true,
          "content": {
            "application/x-tar": {
              "schema": {
                "type": "string",
                "format": "binary"
              }
            }
          }
        }
      },
      "get": {
        "tags": [
          "captures"
        ],
        "summary": "Download Capture Tar",
        "operationId": "download_capture_tar",
        "parameters": [
          {
            "name": "id",
            "in": "path",
            "required": true,
            "schema": {
              "type": "string",
              "format": "uuid",
              "title": "Id"
            }
          }
        ],
        "responses": {
          "307": {
            "description": "Successful Response",
            "content": {
              "application/json": {
                "schema": {}
              }
            }
          },
          "200": {
            "content": {
              "application/x-tar": {
                "schema": {
                  "type": "string",
                  "format": "binary"
                }
              }
            },
            "description": "OK"
          },
          "422": {
            "description": "Validation Error",
            "content": {
              "application/json": {
                "schema": {
                  "$ref": "#/components/schemas/HTTPValidationError"
                }
              }
            }
          }
        }
      }
    },
    "/reconstructions": {
      "post": {
        "tags": [
          "reconstructions"
        ],
        "summary": "Create Reconstruction",
        "operationId": "create_reconstruction",
        "parameters": [
          {
            "name": "capture_id",
            "in": "query",
            "required": true,
            "schema": {
              "type": "string",
              "format": "uuid",
              "title": "Capture Id"
            }
          }
        ],
        "responses": {
          "200": {
            "description": "Successful Response",
            "content": {
              "application/json": {
                "schema": {}
              }
            }
          },
          "422": {
            "description": "Validation Error",
            "content": {
              "application/json": {
                "schema": {
                  "$ref": "#/components/schemas/HTTPValidationError"
                }
              }
            }
          }
        }
      }
    },
    "/nodes": {
      "post": {
        "tags": [
          "nodes"
        ],
        "summary": "Create Node",
        "operationId": "create_node",
        "requestBody": {
          "required": true,
          "content": {
            "application/json": {
              "schema": {
                "$ref": "#/components/schemas/NodeModel"
              }
            }
          }
        },
        "responses": {
          "200": {
            "description": "Successful Response",
            "content": {
              "application/json": {
                "schema": {}
              }
            }
          },
          "422": {
            "description": "Validation Error",
            "content": {
              "application/json": {
                "schema": {
                  "$ref": "#/components/schemas/HTTPValidationError"
                }
              }
            }
          }
        }
      },
      "get": {
        "tags": [
          "nodes"
        ],
        "summary": "Get Nodes",
        "operationId": "get_nodes",
        "parameters": [
          {
            "name": "ids",
            "in": "query",
            "required": false,
            "schema": {
              "anyOf": [
                {
                  "type": "array",
                  "items": {
                    "type": "string",
                    "format": "uuid"
                  }
                },
                {
                  "type": "null"
                }
              ],
              "description": "Optional list of Ids to filter by",
              "title": "Ids"
            },
            "description": "Optional list of Ids to filter by"
          }
        ],
        "responses": {
          "200": {
            "description": "Successful Response",
            "content": {
              "application/json": {
                "schema": {
                  "type": "array",
                  "items": {
                    "$ref": "#/components/schemas/NodeModel"
                  },
                  "title": "Response Get Nodes"
                }
              }
            }
          },
          "422": {
            "description": "Validation Error",
            "content": {
              "application/json": {
                "schema": {
                  "$ref": "#/components/schemas/HTTPValidationError"
                }
              }
            }
          }
        }
      }
    },
    "/nodes/{id}": {
      "put": {
        "tags": [
          "nodes"
        ],
        "summary": "Update Node",
        "operationId": "update_node",
        "parameters": [
          {
            "name": "id",
            "in": "path",
            "required": true,
            "schema": {
              "type": "string",
              "format": "uuid",
              "title": "Id"
            }
          }
        ],
        "requestBody": {
          "required": true,
          "content": {
            "application/json": {
              "schema": {
                "$ref": "#/components/schemas/NodeModel"
              }
            }
          }
        },
        "responses": {
          "200": {
            "description": "Successful Response",
            "content": {
              "application/json": {
                "schema": {}
              }
            }
          },
          "422": {
            "description": "Validation Error",
            "content": {
              "application/json": {
                "schema": {
                  "$ref": "#/components/schemas/HTTPValidationError"
                }
              }
            }
          }
        }
      }
    },
    "/nodes/upsert": {
      "put": {
        "tags": [
          "nodes"
        ],
        "summary": "Upsert Nodes",
        "description": "Bulk upsert nodes.\n- If a node has an id and exists \u2192 update it.\n- If a node has an id but doesn't exist \u2192 insert it.\n- If a node has no id \u2192 generate a new UUID and insert it.",
        "operationId": "upsert_nodes",
        "requestBody": {
          "content": {
            "application/json": {
              "schema": {
                "items": {
                  "$ref": "#/components/schemas/NodeModel"
                },
                "type": "array",
                "title": "Nodes"
              }
            }
          },
          "required": true
        },
        "responses": {
          "200": {
            "description": "Successful Response",
            "content": {
              "application/json": {
                "schema": {}
              }
            }
          },
          "422": {
            "description": "Validation Error",
            "content": {
              "application/json": {
                "schema": {
                  "$ref": "#/components/schemas/HTTPValidationError"
                }
              }
            }
          }
        }
      }
    },
    "/nodes/": {
      "delete": {
        "tags": [
          "nodes"
        ],
        "summary": "Delete Nodes",
        "operationId": "delete_nodes",
        "requestBody": {
          "content": {
            "application/json": {
              "schema": {
                "items": {
                  "type": "string",
                  "format": "uuid"
                },
                "type": "array",
                "title": "Ids"
              }
            }
          },
          "required": true
        },
        "responses": {
          "200": {
            "description": "Successful Response",
            "content": {
              "application/json": {
                "schema": {
                  "items": {
                    "type": "string",
                    "format": "uuid"
                  },
                  "type": "array",
                  "title": "Response Delete Nodes"
                }
              }
            }
          },
          "422": {
            "description": "Validation Error",
            "content": {
              "application/json": {
                "schema": {
                  "$ref": "#/components/schemas/HTTPValidationError"
                }
              }
            }
          }
        }
      }
    },
    "/groups": {
      "post": {
        "tags": [
          "groups"
        ],
        "summary": "Create Group",
        "operationId": "create_group",
        "requestBody": {
          "required": true,
          "content": {
            "application/json": {
              "schema": {
                "$ref": "#/components/schemas/GroupModel"
              }
            }
          }
        },
        "responses": {
          "200": {
            "description": "Successful Response",
            "content": {
              "application/json": {
                "schema": {}
              }
            }
          },
          "422": {
            "description": "Validation Error",
            "content": {
              "application/json": {
                "schema": {
                  "$ref": "#/components/schemas/HTTPValidationError"
                }
              }
            }
          }
        }
      },
      "get": {
        "tags": [
          "groups"
        ],
        "summary": "Get Groups",
        "operationId": "get_groups",
        "parameters": [
          {
            "name": "ids",
            "in": "query",
            "required": false,
            "schema": {
              "anyOf": [
                {
                  "type": "array",
                  "items": {
                    "type": "string",
                    "format": "uuid"
                  }
                },
                {
                  "type": "null"
                }
              ],
              "description": "Optional list of Ids to filter by",
              "title": "Ids"
            },
            "description": "Optional list of Ids to filter by"
          }
        ],
        "responses": {
          "200": {
            "description": "Successful Response",
            "content": {
              "application/json": {
                "schema": {
                  "type": "array",
                  "items": {
                    "$ref": "#/components/schemas/GroupModel"
                  },
                  "title": "Response Get Groups"
                }
              }
            }
          },
          "422": {
            "description": "Validation Error",
            "content": {
              "application/json": {
                "schema": {
                  "$ref": "#/components/schemas/HTTPValidationError"
                }
              }
            }
          }
        }
      }
    },
    "/groups/{id}": {
      "put": {
        "tags": [
          "groups"
        ],
        "summary": "Update Group",
        "operationId": "update_group",
        "parameters": [
          {
            "name": "id",
            "in": "path",
            "required": true,
            "schema": {
              "type": "string",
              "format": "uuid",
              "title": "Id"
            }
          }
        ],
        "requestBody": {
          "required": true,
          "content": {
            "application/json": {
              "schema": {
                "$ref": "#/components/schemas/GroupModel"
              }
            }
          }
        },
        "responses": {
          "200": {
            "description": "Successful Response",
            "content": {
              "application/json": {
                "schema": {}
              }
            }
          },
          "422": {
            "description": "Validation Error",
            "content": {
              "application/json": {
                "schema": {
                  "$ref": "#/components/schemas/HTTPValidationError"
                }
              }
            }
          }
        }
      }
    },
    "/groups/upsert": {
      "put": {
        "tags": [
          "groups"
        ],
        "summary": "Upsert Groups",
        "description": "Bulk upsert groups.\n- If a group has an id and exists \u2192 update it.\n- If a group has an id but doesn't exist \u2192 insert it.\n- If a group has no id \u2192 generate a new UUID and insert it.",
        "operationId": "upsert_groups",
        "requestBody": {
          "content": {
            "application/json": {
              "schema": {
                "items": {
                  "$ref": "#/components/schemas/GroupModel"
                },
                "type": "array",
                "title": "Groups"
              }
            }
          },
          "required": true
        },
        "responses": {
          "200": {
            "description": "Successful Response",
            "content": {
              "application/json": {
                "schema": {}
              }
            }
          },
          "422": {
            "description": "Validation Error",
            "content": {
              "application/json": {
                "schema": {
                  "$ref": "#/components/schemas/HTTPValidationError"
                }
              }
            }
          }
        }
      }
    },
    "/groups/": {
      "delete": {
        "tags": [
          "groups"
        ],
        "summary": "Delete Groups",
        "operationId": "delete_groups",
        "requestBody": {
          "content": {
            "application/json": {
              "schema": {
                "items": {
                  "type": "string",
                  "format": "uuid"
                },
                "type": "array",
                "title": "Ids"
              }
            }
          },
          "required": true
        },
        "responses": {
          "200": {
            "description": "Successful Response",
            "content": {
              "application/json": {
                "schema": {
                  "items": {
                    "type": "string",
                    "format": "uuid"
                  },
                  "type": "array",
                  "title": "Response Delete Groups"
                }
              }
            }
          },
          "422": {
            "description": "Validation Error",
            "content": {
              "application/json": {
                "schema": {
                  "$ref": "#/components/schemas/HTTPValidationError"
                }
              }
            }
          }
        }
      }
    },
    "/layers": {
      "post": {
        "tags": [
          "layers"
        ],
        "summary": "Create Layer",
        "operationId": "create_layer",
        "requestBody": {
          "required": true,
          "content": {
            "application/json": {
              "schema": {
                "$ref": "#/components/schemas/LayerModel"
              }
            }
          }
        },
        "responses": {
          "200": {
            "description": "Successful Response",
            "content": {
              "application/json": {
                "schema": {}
              }
            }
          },
          "422": {
            "description": "Validation Error",
            "content": {
              "application/json": {
                "schema": {
                  "$ref": "#/components/schemas/HTTPValidationError"
                }
              }
            }
          }
        }
      },
      "get": {
        "tags": [
          "layers"
        ],
        "summary": "Get Layers",
        "operationId": "get_layers",
        "parameters": [
          {
            "name": "ids",
            "in": "query",
            "required": false,
            "schema": {
              "anyOf": [
                {
                  "type": "array",
                  "items": {
                    "type": "string",
                    "format": "uuid"
                  }
                },
                {
                  "type": "null"
                }
              ],
              "description": "Optional list of Ids to filter by",
              "title": "Ids"
            },
            "description": "Optional list of Ids to filter by"
          }
        ],
        "responses": {
          "200": {
            "description": "Successful Response",
            "content": {
              "application/json": {
                "schema": {
                  "type": "array",
                  "items": {
                    "$ref": "#/components/schemas/LayerModel"
                  },
                  "title": "Response Get Layers"
                }
              }
            }
          },
          "422": {
            "description": "Validation Error",
            "content": {
              "application/json": {
                "schema": {
                  "$ref": "#/components/schemas/HTTPValidationError"
                }
              }
            }
          }
        }
      }
    },
    "/layers/{id}": {
      "put": {
        "tags": [
          "layers"
        ],
        "summary": "Update Layer",
        "operationId": "update_layer",
        "parameters": [
          {
            "name": "id",
            "in": "path",
            "required": true,
            "schema": {
              "type": "string",
              "format": "uuid",
              "title": "Id"
            }
          }
        ],
        "requestBody": {
          "required": true,
          "content": {
            "application/json": {
              "schema": {
                "$ref": "#/components/schemas/LayerModel"
              }
            }
          }
        },
        "responses": {
          "200": {
            "description": "Successful Response",
            "content": {
              "application/json": {
                "schema": {}
              }
            }
          },
          "422": {
            "description": "Validation Error",
            "content": {
              "application/json": {
                "schema": {
                  "$ref": "#/components/schemas/HTTPValidationError"
                }
              }
            }
          }
        }
      }
    },
    "/layers/upsert": {
      "put": {
        "tags": [
          "layers"
        ],
        "summary": "Upsert Layers",
        "description": "Bulk upsert layers.\n- If a layer has an id and exists \u2192 update it.\n- If a layer has an id but doesn't exist \u2192 insert it.\n- If a layer has no id \u2192 generate a new UUID and insert it.",
        "operationId": "upsert_layers",
        "requestBody": {
          "content": {
            "application/json": {
              "schema": {
                "items": {
                  "$ref": "#/components/schemas/LayerModel"
                },
                "type": "array",
                "title": "Layers"
              }
            }
          },
          "required": true
        },
        "responses": {
          "200": {
            "description": "Successful Response",
            "content": {
              "application/json": {
                "schema": {}
              }
            }
          },
          "422": {
            "description": "Validation Error",
            "content": {
              "application/json": {
                "schema": {
                  "$ref": "#/components/schemas/HTTPValidationError"
                }
              }
            }
          }
        }
      }
    },
    "/layers/": {
      "delete": {
        "tags": [
          "layers"
        ],
        "summary": "Delete Layers",
        "operationId": "delete_layers",
        "requestBody": {
          "content": {
            "application/json": {
              "schema": {
                "items": {
                  "type": "string",
                  "format": "uuid"
                },
                "type": "array",
                "title": "Ids"
              }
            }
          },
          "required": true
        },
        "responses": {
          "200": {
            "description": "Successful Response",
            "content": {
              "application/json": {
                "schema": {
                  "items": {
                    "type": "string",
                    "format": "uuid"
                  },
                  "type": "array",
                  "title": "Response Delete Layers"
                }
              }
            }
          },
          "422": {
            "description": "Validation Error",
            "content": {
              "application/json": {
                "schema": {
                  "$ref": "#/components/schemas/HTTPValidationError"
                }
              }
            }
          }
        }
      }
    },
    "/localizationMaps": {
      "post": {
        "tags": [
          "localizationMaps"
        ],
        "summary": "Create Localizationmap",
        "operationId": "create_localizationMap",
        "requestBody": {
          "required": true,
          "content": {
            "application/json": {
              "schema": {
                "$ref": "#/components/schemas/LocalizationMapModel"
              }
            }
          }
        },
        "responses": {
          "200": {
            "description": "Successful Response",
            "content": {
              "application/json": {
                "schema": {}
              }
            }
          },
          "422": {
            "description": "Validation Error",
            "content": {
              "application/json": {
                "schema": {
                  "$ref": "#/components/schemas/HTTPValidationError"
                }
              }
            }
          }
        }
      },
      "get": {
        "tags": [
          "localizationMaps"
        ],
        "summary": "Get Localizationmaps",
        "operationId": "get_localizationMaps",
        "parameters": [
          {
            "name": "ids",
            "in": "query",
            "required": false,
            "schema": {
              "anyOf": [
                {
                  "type": "array",
                  "items": {
                    "type": "string",
                    "format": "uuid"
                  }
                },
                {
                  "type": "null"
                }
              ],
              "description": "Optional list of Ids to filter by",
              "title": "Ids"
            },
            "description": "Optional list of Ids to filter by"
          }
        ],
        "responses": {
          "200": {
            "description": "Successful Response",
            "content": {
              "application/json": {
                "schema": {
                  "type": "array",
                  "items": {
                    "$ref": "#/components/schemas/LocalizationMapModel"
                  },
                  "title": "Response Get Localizationmaps"
                }
              }
            }
          },
          "422": {
            "description": "Validation Error",
            "content": {
              "application/json": {
                "schema": {
                  "$ref": "#/components/schemas/HTTPValidationError"
                }
              }
            }
          }
        }
      }
    },
    "/localizationMaps/{id}": {
      "put": {
        "tags": [
          "localizationMaps"
        ],
        "summary": "Update Localizationmap",
        "operationId": "update_localizationMap",
        "parameters": [
          {
            "name": "id",
            "in": "path",
            "required": true,
            "schema": {
              "type": "string",
              "format": "uuid",
              "title": "Id"
            }
          }
        ],
        "requestBody": {
          "required": true,
          "content": {
            "application/json": {
              "schema": {
                "$ref": "#/components/schemas/LocalizationMapModel"
              }
            }
          }
        },
        "responses": {
          "200": {
            "description": "Successful Response",
            "content": {
              "application/json": {
                "schema": {}
              }
            }
          },
          "422": {
            "description": "Validation Error",
            "content": {
              "application/json": {
                "schema": {
                  "$ref": "#/components/schemas/HTTPValidationError"
                }
              }
            }
          }
        }
      }
    },
    "/localizationMaps/upsert": {
      "put": {
        "tags": [
          "localizationMaps"
        ],
        "summary": "Upsert Localizationmaps",
        "description": "Bulk upsert localizationMaps.\n- If a localizationMap has an id and exists \u2192 update it.\n- If a localizationMap has an id but doesn't exist \u2192 insert it.\n- If a localizationMap has no id \u2192 generate a new UUID and insert it.",
        "operationId": "upsert_localizationMaps",
        "requestBody": {
          "content": {
            "application/json": {
              "schema": {
                "items": {
                  "$ref": "#/components/schemas/LocalizationMapModel"
                },
                "type": "array",
                "title": "Localizationmaps"
              }
            }
          },
          "required": true
        },
        "responses": {
          "200": {
            "description": "Successful Response",
            "content": {
              "application/json": {
                "schema": {}
              }
            }
          },
          "422": {
            "description": "Validation Error",
            "content": {
              "application/json": {
                "schema": {
                  "$ref": "#/components/schemas/HTTPValidationError"
                }
              }
            }
          }
        }
      }
    },
    "/localizationMaps/": {
      "delete": {
        "tags": [
          "localizationMaps"
        ],
        "summary": "Delete Localizationmaps",
        "operationId": "delete_localizationMaps",
        "requestBody": {
          "content": {
            "application/json": {
              "schema": {
                "items": {
                  "type": "string",
                  "format": "uuid"
                },
                "type": "array",
                "title": "Ids"
              }
            }
          },
          "required": true
        },
        "responses": {
          "200": {
            "description": "Successful Response",
            "content": {
              "application/json": {
                "schema": {
                  "items": {
                    "type": "string",
                    "format": "uuid"
                  },
                  "type": "array",
                  "title": "Response Delete Localizationmaps"
                }
              }
            }
          },
          "422": {
            "description": "Validation Error",
            "content": {
              "application/json": {
                "schema": {
                  "$ref": "#/components/schemas/HTTPValidationError"
                }
              }
            }
          }
        }
      }
    }
  },
  "components": {
    "schemas": {
      "Body_create_capture": {
        "properties": {
          "id": {
            "type": "string",
            "format": "uuid",
            "title": "Id"
          },
          "filename": {
            "type": "string",
            "title": "Filename"
          }
        },
        "type": "object",
        "required": [
          "id",
          "filename"
        ],
        "title": "Body_create_capture"
      },
      "CaptureModel": {
        "properties": {
          "id": {
            "type": "string",
            "format": "uuid",
            "title": "Id",
            "extra": {
              "nullable": false,
              "secret": false,
              "unique": false
            }
          },
          "filename": {
            "type": "string",
            "maxLength": 255,
            "title": "Filename",
            "extra": {
              "nullable": false,
              "secret": false,
              "unique": true
            }
          },
          "created_at": {
            "type": "string",
            "format": "date-time",
            "title": "Created At",
            "extra": {
              "nullable": false,
              "secret": false,
              "unique": false
            }
          },
          "uploaded_at": {
            "anyOf": [
              {
                "type": "string",
                "format": "date-time"
              },
              {
                "type": "null"
              }
            ],
            "title": "Uploaded At",
            "extra": {
              "nullable": true,
              "secret": false,
              "unique": false
            }
          }
        },
        "type": "object",
        "required": [
          "id",
          "filename",
          "created_at"
        ],
        "title": "CaptureModel",
        "extra": {}
      },
      "GroupModel": {
        "properties": {
          "id": {
            "type": "string",
            "format": "uuid",
            "title": "Id",
            "extra": {
              "nullable": false,
              "secret": false,
              "unique": false
            }
          },
          "name": {
            "type": "string",
            "maxLength": 255,
            "title": "Name",
            "extra": {
              "nullable": false,
              "secret": false,
              "unique": true
            }
          },
          "parent": {
            "anyOf": [
              {
                "type": "string",
                "format": "uuid"
              },
              {
                "type": "null"
              }
            ],
            "title": "Parent",
            "extra": {
              "nullable": true,
              "secret": false,
              "unique": false
            }
          }
        },
        "type": "object",
        "required": [
          "id",
          "name"
        ],
        "title": "GroupModel",
        "extra": {}
      },
      "HTTPValidationError": {
        "properties": {
          "detail": {
            "items": {
              "$ref": "#/components/schemas/ValidationError"
            },
            "type": "array",
            "title": "Detail"
          }
        },
        "type": "object",
        "title": "HTTPValidationError"
      },
      "LayerModel": {
        "properties": {
          "id": {
            "type": "string",
            "format": "uuid",
            "title": "Id",
            "extra": {
              "nullable": false,
              "secret": false,
              "unique": false
            }
          },
          "name": {
            "type": "string",
            "maxLength": 255,
            "title": "Name",
            "extra": {
              "nullable": false,
              "secret": false,
              "unique": true
            }
          }
        },
        "type": "object",
        "required": [
          "id",
          "name"
        ],
        "title": "LayerModel",
        "extra": {}
      },
      "LocalizationMapModel": {
        "properties": {
          "id": {
            "type": "string",
            "format": "uuid",
            "title": "Id",
            "extra": {
              "nullable": false,
              "secret": false,
              "unique": false
            }
          },
          "name": {
            "type": "string",
            "maxLength": 255,
            "title": "Name",
            "extra": {
              "nullable": false,
              "secret": false,
              "unique": true
            }
          },
          "active": {
            "type": "boolean",
            "title": "Active",
            "extra": {
              "nullable": false,
              "secret": false,
              "unique": false
            }
          },
          "lighting": {
            "type": "integer",
            "title": "Lighting",
            "extra": {
              "nullable": false,
              "secret": false,
              "unique": false
            }
          },
          "color": {
            "type": "integer",
            "title": "Color",
            "extra": {
              "nullable": false,
              "secret": false,
              "unique": false
            }
          },
          "positionX": {
            "type": "number",
            "title": "Positionx",
            "extra": {
              "nullable": false,
              "secret": false,
              "unique": false
            }
          },
          "positionY": {
            "type": "number",
            "title": "Positiony",
            "extra": {
              "nullable": false,
              "secret": false,
              "unique": false
            }
          },
          "positionZ": {
            "type": "number",
            "title": "Positionz",
            "extra": {
              "nullable": false,
              "secret": false,
              "unique": false
            }
          },
          "rotationX": {
            "type": "number",
            "title": "Rotationx",
            "extra": {
              "nullable": false,
              "secret": false,
              "unique": false
            }
          },
          "rotationY": {
            "type": "number",
            "title": "Rotationy",
            "extra": {
              "nullable": false,
              "secret": false,
              "unique": false
            }
          },
          "rotationZ": {
            "type": "number",
            "title": "Rotationz",
            "extra": {
              "nullable": false,
              "secret": false,
              "unique": false
            }
          },
          "rotationW": {
            "type": "number",
            "title": "Rotationw",
            "extra": {
              "nullable": false,
              "secret": false,
              "unique": false
            }
          },
          "points": {
            "anyOf": [
              {
                "items": {
                  "type": "number"
                },
                "type": "array"
              },
              {
                "type": "null"
              }
            ],
            "title": "Points",
            "extra": {
              "dimensions": 1,
              "nullable": false,
              "secret": false,
              "unique": false
            }
          }
        },
        "type": "object",
        "required": [
          "id",
          "name",
          "active",
          "lighting",
          "color",
          "positionX",
          "positionY",
          "positionZ",
          "rotationX",
          "rotationY",
          "rotationZ",
          "rotationW"
        ],
        "title": "LocalizationMapModel",
        "extra": {}
      },
      "NodeModel": {
        "properties": {
          "id": {
            "type": "string",
            "format": "uuid",
            "title": "Id",
            "extra": {
              "nullable": false,
              "secret": false,
              "unique": false
            }
          },
          "name": {
            "type": "string",
            "maxLength": 255,
            "title": "Name",
            "extra": {
              "nullable": false,
              "secret": false,
              "unique": true
            }
          },
          "created_at": {
            "anyOf": [
              {
                "type": "string",
                "format": "date-time"
              },
              {
                "type": "null"
              }
            ],
            "title": "Created At",
            "extra": {
              "nullable": true,
              "secret": false,
              "unique": false
            }
          },
          "active": {
            "type": "boolean",
            "title": "Active",
            "extra": {
              "nullable": false,
              "secret": false,
              "unique": false
            }
          },
          "positionX": {
            "type": "number",
            "title": "Positionx",
            "extra": {
              "nullable": false,
              "secret": false,
              "unique": false
            }
          },
          "positionY": {
            "type": "number",
            "title": "Positiony",
            "extra": {
              "nullable": false,
              "secret": false,
              "unique": false
            }
          },
          "positionZ": {
            "type": "number",
            "title": "Positionz",
            "extra": {
              "nullable": false,
              "secret": false,
              "unique": false
            }
          },
          "rotationX": {
            "type": "number",
            "title": "Rotationx",
            "extra": {
              "nullable": false,
              "secret": false,
              "unique": false
            }
          },
          "rotationY": {
            "type": "number",
            "title": "Rotationy",
            "extra": {
              "nullable": false,
              "secret": false,
              "unique": false
            }
          },
          "rotationZ": {
            "type": "number",
            "title": "Rotationz",
            "extra": {
              "nullable": false,
              "secret": false,
              "unique": false
            }
          },
          "rotationW": {
            "type": "number",
            "title": "Rotationw",
            "extra": {
              "nullable": false,
              "secret": false,
              "unique": false
            }
          },
          "labelType": {
            "anyOf": [
              {
                "type": "integer"
              },
              {
                "type": "null"
              }
            ],
            "title": "Labeltype",
            "extra": {
              "nullable": true,
              "secret": false,
              "unique": false
            }
          },
          "label": {
            "anyOf": [
              {
                "type": "string",
                "maxLength": 255
              },
              {
                "type": "null"
              }
            ],
            "title": "Label",
            "extra": {
              "nullable": true,
              "secret": false,
              "unique": false
            }
          },
          "linkType": {
            "anyOf": [
              {
                "type": "integer"
              },
              {
                "type": "null"
              }
            ],
            "title": "Linktype",
            "extra": {
              "nullable": true,
              "secret": false,
              "unique": false
            }
          },
          "link": {
            "anyOf": [
              {
                "type": "string",
                "maxLength": 255
              },
              {
                "type": "null"
              }
            ],
            "title": "Link",
            "extra": {
              "nullable": true,
              "secret": false,
              "unique": false
            }
          },
          "labelScale": {
            "anyOf": [
              {
                "type": "number"
              },
              {
                "type": "null"
              }
            ],
            "title": "Labelscale",
            "extra": {
              "nullable": true,
              "secret": false,
              "unique": false
            }
          },
          "labelWidth": {
            "anyOf": [
              {
                "type": "number"
              },
              {
                "type": "null"
              }
            ],
            "title": "Labelwidth",
            "extra": {
              "nullable": true,
              "secret": false,
              "unique": false
            }
          },
          "labelHeight": {
            "anyOf": [
              {
                "type": "number"
              },
              {
                "type": "null"
              }
            ],
            "title": "Labelheight",
            "extra": {
              "nullable": true,
              "secret": false,
              "unique": false
            }
          },
          "parent": {
            "anyOf": [
              {
                "type": "string",
                "format": "uuid"
              },
              {
                "type": "null"
              }
            ],
            "title": "Parent",
            "extra": {
              "nullable": true,
              "secret": false,
              "unique": false
            }
          },
          "layer": {
            "anyOf": [
              {
                "type": "string",
                "format": "uuid"
              },
              {
                "type": "null"
              }
            ],
            "title": "Layer",
            "extra": {
              "nullable": true,
              "secret": false,
              "unique": false
            }
          }
        },
        "type": "object",
        "required": [
          "id",
          "name",
          "active",
          "positionX",
          "positionY",
          "positionZ",
          "rotationX",
          "rotationY",
          "rotationZ",
          "rotationW"
        ],
        "title": "NodeModel",
        "extra": {}
      },
      "ValidationError": {
        "properties": {
          "loc": {
            "items": {
              "anyOf": [
                {
                  "type": "string"
                },
                {
                  "type": "integer"
                }
              ]
            },
            "type": "array",
            "title": "Location"
          },
          "msg": {
            "type": "string",
            "title": "Message"
          },
          "type": {
            "type": "string",
            "title": "Error Type"
          }
        },
        "type": "object",
        "required": [
          "loc",
          "msg",
          "type"
        ],
        "title": "ValidationError"
      }
    }
  }
}